{
  "type": "pdf",
  "path": "D:\\Source Code\\lemur-pageindex\\pageindex-engine\\workspace\\uploads\\44454157-d710-4070-84c7-811e0259b71f\\ca1f30aa-ec16-4dd5-9162-593ebb442468.pdf",
  "doc_name": "ca1f30aa-ec16-4dd5-9162-593ebb442468.pdf",
  "doc_description": "VA Pamphlet 26-7, Revised Chapter 17: VA Sanctions Against Program Participants 17-1 Chapter 17 VA Sanctions Against Program Participants Overview Introduction VA is authorized to impose sanctions against persons or entities who take actions which are detrimental to the VA loan guaranty program. The type and severity of the sanction imposed is based on ...",
  "page_count": 25,
  "structure": [
    {
      "title": "VA Pamphlet 26-7, Revised Chapter 17: VA Sanctions Against Program Participants",
      "node_id": "0000",
      "start_index": 1,
      "end_index": 8,
      "summary": "VA Pamphlet 26-7, Revised Chapter 17: VA Sanctions Against Program Participants 17-1 Chapter 17 VA Sanctions Against Program Participants Overview Introduction VA is authorized to impose sanctions against persons or entities who take actions which are detrimental to the VA loan guaranty program. The type and severity...",
      "nodes": [
        {
          "title": "VA Pamphlet 26-7, Revised Chapter 17: VA Sanctions Against Program Participants",
          "node_id": "0001",
          "start_index": 1,
          "end_index": 1,
          "summary": "VA Pamphlet 26-7, Revised Chapter 17: VA Sanctions Against Program Participants 17-1 Chapter 17 VA Sanctions Against Program Participants Overview Introduction VA is authorized to impose sanctions against persons or..."
        },
        {
          "title": "Chapter 17: VA Sanctions Against Program Participants VA Pamphlet 26-7, Revised",
          "node_id": "0002",
          "start_index": 2,
          "end_index": 2,
          "summary": "Chapter 17: VA Sanctions Against Program Participants VA Pamphlet 26-7, Revised 17-2 17.01 Program Participants Program Participants Any person or entity conducting busin ess related to the VA loan guaranty program is..."
        },
        {
          "title": "VA Pamphlet 26-7, Revised Chapter 17: VA Sanctions Against Program Participants",
          "node_id": "0003",
          "start_index": 3,
          "end_index": 3,
          "summary": "VA Pamphlet 26-7, Revised Chapter 17: VA Sanctions Against Program Participants 17-3 17.01 Program Participants, Continued Full Exclusion A participant who is fully excluded may not  conduct any type of VA loan..."
        },
        {
          "title": "Chapter 17: VA Sanctions Against Program Participants VA Pamphlet 26-7, Revised",
          "node_id": "0004",
          "start_index": 4,
          "end_index": 4,
          "summary": "Chapter 17: VA Sanctions Against Program Participants VA Pamphlet 26-7, Revised 17-4 17.01 Program Participants, Continued Nature of Exclusion Some of the parties on this list may be excluded from  participation in the..."
        },
        {
          "title": "VA Pamphlet 26-7, Revised Chapter 17: VA Sanctions Against Program Participants",
          "node_id": "0005",
          "start_index": 5,
          "end_index": 5,
          "summary": "VA Pamphlet 26-7, Revised Chapter 17: VA Sanctions Against Program Participants 17-5 17.01 Program Participants, Continued Lender Check On Excluded Parties Lenders and other parties may want to check whether a program..."
        },
        {
          "title": "Chapter 17: VA Sanctions Against Program Participants VA Pamphlet 26-7, Revised",
          "node_id": "0006",
          "start_index": 6,
          "end_index": 6,
          "summary": "Chapter 17: VA Sanctions Against Program Participants VA Pamphlet 26-7, Revised 17-6 17.02 False Lender Certification Lender Certification A lender must submit a signed certif ication with each loan submission..."
        },
        {
          "title": "VA Pamphlet 26-7, Revised Chapter 17: VA Sanctions Against Program Participants",
          "node_id": "0007",
          "start_index": 7,
          "end_index": 7,
          "summary": "VA Pamphlet 26-7, Revised Chapter 17: VA Sanctions Against Program Participants 17-7 17.03 Withdrawal of Automatic Authority Withdrawal For Proper Cause VA can withdraw a lender’s automatic au thority for proper cause,..."
        },
        {
          "title": "Chapter 17: VA Sanctions Against Program Participants VA Pamphlet 26-7, Revised",
          "node_id": "0008",
          "start_index": 8,
          "end_index": 8,
          "summary": "Chapter 17: VA Sanctions Against Program Participants VA Pamphlet 26-7, Revised 17-8 17.03 Withdrawal of Automatic Authority, Continued Withdrawal Time Periods Refer to the following table for info rmation on withdrawal..."
        }
      ]
    },
    {
      "title": "VA Pamphlet 26-7, Revised Chapter 17: VA Sanctions Against Program Participants",
      "node_id": "0009",
      "start_index": 9,
      "end_index": 16,
      "summary": "VA Pamphlet 26-7, Revised Chapter 17: VA Sanctions Against Program Participants 17-9 17.03 Withdrawal of Automatic Authority, Continued Withdrawal Period: 180 Days A withdrawal period of 180 days can be based on any of the following situations:  Loans conflict with VA credit standard s and would not have been made by...",
      "nodes": [
        {
          "title": "VA Pamphlet 26-7, Revised Chapter 17: VA Sanctions Against Program Participants",
          "node_id": "0010",
          "start_index": 9,
          "end_index": 9,
          "summary": "VA Pamphlet 26-7, Revised Chapter 17: VA Sanctions Against Program Participants 17-9 17.03 Withdrawal of Automatic Authority, Continued Withdrawal Period: 180 Days A withdrawal period of 180 days can be based on any of..."
        },
        {
          "title": "Chapter 17: VA Sanctions Against Program Participants VA Pamphlet 26-7, Revised",
          "node_id": "0011",
          "start_index": 10,
          "end_index": 10,
          "summary": "Chapter 17: VA Sanctions Against Program Participants VA Pamphlet 26-7, Revised 17-10 17.03 Withdrawal of Automatic Authority, Continued Withdrawal Period: 1-3 Years A withdrawal period of 1- 3 years can be based on any..."
        },
        {
          "title": "VA Pamphlet 26-7, Revised Chapter 17: VA Sanctions Against Program Participants",
          "node_id": "0012",
          "start_index": 11,
          "end_index": 11,
          "summary": "VA Pamphlet 26-7, Revised Chapter 17: VA Sanctions Against Program Participants 17-11 17.04 Withdrawal of LAPP Authority LAPP is a Privilege The authority to determine value under LAPP is a privilege delegated to..."
        },
        {
          "title": "Chapter 17: VA Sanctions Against Program Participants VA Pamphlet 26-7, Revised",
          "node_id": "0013",
          "start_index": 12,
          "end_index": 12,
          "summary": "Chapter 17: VA Sanctions Against Program Participants VA Pamphlet 26-7, Revised 17-12 17.04 Withdrawal of LAPP Authority, Continued Examples of Withdrawal for Proper Cause The following is a non-inclusive list of..."
        },
        {
          "title": "VA Pamphlet 26-7, Revised Chapter 17: VA Sanctions Against Program Participants",
          "node_id": "0014",
          "start_index": 13,
          "end_index": 13,
          "summary": "VA Pamphlet 26-7, Revised Chapter 17: VA Sanctions Against Program Participants 17-13 17.04 Withdrawal of LAPP Authority, Continued Notice of Sanction Generally, VA will provide written notice at least 30 days prior to..."
        },
        {
          "title": "Chapter 17: VA Sanctions Against Program Participants VA Pamphlet 26-7, Revised",
          "node_id": "0015",
          "start_index": 14,
          "end_index": 14,
          "summary": "Chapter 17: VA Sanctions Against Program Participants VA Pamphlet 26-7, Revised 17-14 17.04 Withdrawal of LAPP Authority, Continued Other Sanctions Withdrawal or amendment of a lende r’s LAPP authority does not preclude..."
        },
        {
          "title": "VA Pamphlet 26-7, Revised Chapter 17: VA Sanctions Against Program Participants",
          "node_id": "0016",
          "start_index": 15,
          "end_index": 15,
          "summary": "VA Pamphlet 26-7, Revised Chapter 17: VA Sanctions Against Program Participants 17-15 17.05 Debarment and Suspension Debarment Debarment is a sanction that in most cases excludes the program participant from any..."
        },
        {
          "title": "Chapter 17: VA Sanctions Against Program Participants VA Pamphlet 26-7, Revised",
          "node_id": "0017",
          "start_index": 16,
          "end_index": 16,
          "summary": "Chapter 17: VA Sanctions Against Program Participants VA Pamphlet 26-7, Revised 17-16 17.05 Debarment and Suspension, Continued Geographic Scope of Exclusion The debarred or suspended participant is excluded from..."
        }
      ]
    },
    {
      "title": "VA Pamphlet 26-7, Revised Chapter 17: VA Sanctions Against Program Participants",
      "node_id": "0018",
      "start_index": 17,
      "end_index": 24,
      "summary": "VA Pamphlet 26-7, Revised Chapter 17: VA Sanctions Against Program Participants 17-17 17.05 Debarment and Suspension, Continued Causes for Debarment or Suspension The regulations authorize VA to debar or suspend participants for “Any other cause of so serious or compelling a nature that it affects the present...",
      "nodes": [
        {
          "title": "VA Pamphlet 26-7, Revised Chapter 17: VA Sanctions Against Program Participants",
          "node_id": "0019",
          "start_index": 17,
          "end_index": 17,
          "summary": "VA Pamphlet 26-7, Revised Chapter 17: VA Sanctions Against Program Participants 17-17 17.05 Debarment and Suspension, Continued Causes for Debarment or Suspension The regulations authorize VA to debar or suspend..."
        },
        {
          "title": "Chapter 17: VA Sanctions Against Program Participants VA Pamphlet 26-7, Revised",
          "node_id": "0020",
          "start_index": 18,
          "end_index": 18,
          "summary": "Chapter 17: VA Sanctions Against Program Participants VA Pamphlet 26-7, Revised 17-18 17.06 Limited Denial of Participation (LDP) Introduction A Limited Denial of Participation (LDP)  is a sanction imposed by a local..."
        },
        {
          "title": "VA Pamphlet 26-7, Revised Chapter 17: VA Sanctions Against Program Participants",
          "node_id": "0021",
          "start_index": 19,
          "end_index": 19,
          "summary": "VA Pamphlet 26-7, Revised Chapter 17: VA Sanctions Against Program Participants 17-19 17.06 Limited Denial of Participation (LDP), Continued Causes for LDP VA can impose LDPs based on any of a multitude of causes..."
        },
        {
          "title": "Chapter 17: VA Sanctions Against Program Participants VA Pamphlet 26-7, Revised",
          "node_id": "0022",
          "start_index": 20,
          "end_index": 20,
          "summary": "Chapter 17: VA Sanctions Against Program Participants VA Pamphlet 26-7, Revised 17-20 17.06 Limited Denial of Participation (LDP), Continued Appeal Rights No additional appeal rights are provided to the participant for..."
        },
        {
          "title": "VA Pamphlet 26-7, Revised Chapter 17: VA Sanctions Against Program Participants",
          "node_id": "0023",
          "start_index": 21,
          "end_index": 21,
          "summary": "VA Pamphlet 26-7, Revised Chapter 17: VA Sanctions Against Program Participants 17-21 17.07 Unfair Contract Provis ions or Marketing Practices Introduction VA may impose sanctions, such as de barment, suspension, or LDP..."
        },
        {
          "title": "Chapter 17: VA Sanctions Against Program Participants VA Pamphlet 26-7, Revised",
          "node_id": "0024",
          "start_index": 22,
          "end_index": 22,
          "summary": "Chapter 17: VA Sanctions Against Program Participants VA Pamphlet 26-7, Revised 17-22 17.07 Unfair Contract Provis ions or Marketing Practices, Continued Unfair Marketing Practices Unfair marketing practices include,..."
        },
        {
          "title": "VA Pamphlet 26-7, Revised Chapter 17: VA Sanctions Against Program Participants",
          "node_id": "0025",
          "start_index": 23,
          "end_index": 23,
          "summary": "VA Pamphlet 26-7, Revised Chapter 17: VA Sanctions Against Program Participants 17-23 17.08 Violations of Equal Housing Opportunity Laws Introduction VA may impose sanctions, such as de barment, suspension, or LDP..."
        },
        {
          "title": "Chapter 17: VA Sanctions Against Program Participants VA Pamphlet 26-7, Revised",
          "node_id": "0026",
          "start_index": 24,
          "end_index": 24,
          "summary": "Chapter 17: VA Sanctions Against Program Participants VA Pamphlet 26-7, Revised 17-24 17.08 Violations of Equa l Housing Opportunity Laws, Continued Equal Housing Certification This regulation requires a certification..."
        }
      ]
    },
    {
      "title": "VA Pamphlet 26-7, Revised Chapter 17: VA Sanctions Against Program Participants",
      "node_id": "0027",
      "start_index": 25,
      "end_index": 25,
      "summary": "VA Pamphlet 26-7, Revised Chapter 17: VA Sanctions Against Program Participants 17-25 Amend or Withdraw the Special Privilege of LAPP Authority, 17-11 Appeal Rights to all Program Participants, 17-1 Cause and Treatment Codes, 17-4 Causes for LDP, 17-19 Debarment, 17-15 Debarment or Suspension Causes, 17-17 Debarred...",
      "nodes": [
        {
          "title": "VA Pamphlet 26-7, Revised Chapter 17: VA Sanctions Against Program Participants",
          "node_id": "0028",
          "start_index": 25,
          "end_index": 25,
          "summary": "VA Pamphlet 26-7, Revised Chapter 17: VA Sanctions Against Program Participants 17-25 Amend or Withdraw the Special Privilege of LAPP Authority, 17-11 Appeal Rights to all Program Participants, 17-1 Cause and Treatment..."
        }
      ]
    }
  ],
  "pages": [
    {
      "page": 1,
      "content": "VA Pamphlet 26-7, Revised  Chapter 17:  VA Sanctions Against Program Participants  \n  17-1  Chapter 17 \nVA Sanctions Against Program Participants \nOverview \n \nIntroduction VA is authorized to impose sanctions against persons or entities who take \nactions which are detrimental to the VA loan guaranty program.  The type and \nseverity of the sanction imposed is based on  \n the type of participant (for example,  lender, builder, ma nagement broker, \netc.), and \n the nature of the actions  (for example., fraud, signif icant deficiencies in \nperformance, ongoing disregard for VA requirements, and so on). \n \nSanctions may be imposed in the form of  \n civil money penalties, and/or \n the participant’s full or partial exclusion from participation in the VA loan  \nguaranty program for a certain period of time. \n \nAppeal Rights VA provides appeal rights to all progra m participants agai nst whom sanctions \nare imposed.  The notice informing the pa rticipant that sanctions will be or \nare imposed explains what the particip ant must do to appeal VA’s decision. \n \nIn this Chapter This chapter contains the followin g topics. \n \nTopic See Page \n17.01  Pro gram Participants 17-2 \n17.02  False Lender Certificatio n 17-6 \n17.03  Withdrawal of Automatic Authorit y 17-7 \n17.04  Withdrawal of LAPP Authorit y 17-11 \n17.05  Debarment and Suspensio n 17-15 \n17.06  Limited Denial of Participation (LDP) 17-18 \n17.07  Unfair Contract Provisions or Marketin g Practices 17-21 \n17.08  Violations of Equal Housin g Opportunit y Laws 17-23"
    },
    {
      "page": 2,
      "content": "Chapter 17:  VA Sanctions Against Program Participants VA Pamphlet 26-7, Revised  \n17-2   17.01  Program Participants \n \nProgram \nParticipants Any person or entity conducting busin ess related to the VA loan guaranty \nprogram is considered a progr am participant.  This includes, but is not limited \nto  \n lenders \n employees of lenders \n loan holders \n loan servicers \n builders \n real estate brokers or agents \n management brokers \n repair contractors \n compliance inspectors \n fee appraisers \n salespersons, and \n manufactured home manufacturers,  dealers or park operators. \n \nNote :  A person is not considered a program particip ant just because he or she \nobtains a VA loan. \n \nProgram \nParticipant Also A Veteran VA may impose sanctions against a program  participant who is also a veteran \neligible for loan guaranty benefits.  Th is does not preclude the veteran from \nusing his or her entitlement to obtain a VA- guaranteed loan. \n \nContinued on next page"
    },
    {
      "page": 3,
      "content": "VA Pamphlet 26-7, Revised  Chapter 17:  VA Sanctions Against Program Participants  \n  17-3  17.01  Program Participants, Continued \n \nFull Exclusion A participant who is fully excluded may not \n \n conduct any type of VA loan  guaranty business, or \n have another party conduct such  business on his or her behalf. \n \nPartial \nExclusion Partial exclusion may in volve limitations on \n \n the role the participant may play, or \n how the participant conducts  VA loan guaranty business. \n \nProgram \nParticipants \nand Excluded \nParties Program participants may not \n \n do VA business with an excluded party if the type of transaction involved is \nprohibited by the terms of the party’s exclusion, or \n allow an employed excluded party to perform prohibited duties. \n \nViolation of the above re strictions may result in VA sanctions against the \nprogram participant doin g business with (or emplo ying) the excluded part y. \n \nIdentifying \nExcluded \nParties Participants may check the List of Parties Excluded From Federal \nProcurement and Nonprocurement Programs  published by the U.S. General \nServices Administration (GSA).  The list can be obtained  \n in hard copy by subscription through the Superintendent of Documents, \nU.S. Government Printing Office, Washington, DC  20402, and \n electronically, via the Internet at www.epls.arnet@gsa/gov . \n \nNote :  Contact GSA at (2 02)501-4740, or, online at epls.support@gsa.gov  for \ndetails. \n \nContinued on next page"
    },
    {
      "page": 4,
      "content": "Chapter 17:  VA Sanctions Against Program Participants VA Pamphlet 26-7, Revised  \n17-4   17.01  Program Participants, Continued \n \nNature of \nExclusion Some of the parties on this list may be excluded from \n \n participation in the programs of all Federal agencies, including VA, or \n a specific program of a specific Federal agency. \n \nCause and \nTreatment \nCodes The cause and treatment codes provide  information on the nature of the \nexclusion.  These codes are described in the document and at the GSA \nwebsite, above .   \n \nObtaining \nInformation on \nExcluded Party Call the contact person for the agency that placed the excluded party on the \nlist if   \n more detail is necessary to confirm th e identity of a party on the list, or \n to clarify the nature or length of the sanction. \n \nNon-\nprocurement \nList  For parties placed on th e non-procurement list  by VA (indicated by the code \n“VA”), obtain any necessary clarifyi ng information from the local VA office \nwith jurisdiction over the cit y and state listed in  the excluded part y’s address. \n \nParties Not on \nGSA List Some of the VA sanctioned parties may not appear on the GSA list.  \nInformation on such parties can be obtained by contacting the local VA \noffice. \n \nContinued on next page"
    },
    {
      "page": 5,
      "content": "VA Pamphlet 26-7, Revised  Chapter 17:  VA Sanctions Against Program Participants  \n  17-5  17.01  Program Participants, Continued \n \nLender Check \nOn Excluded \nParties Lenders and other parties may want to  check whether a program participant \nhas been excluded prior to  \n employing the program  participant, or \n participating in a VA loan guaranty-related transaction, if  the program \nparticipant is also a pa rty to the transaction. \n \nNote :  This does not refer to a veteran usin g entitlement to obtain a VA loan. \n \nReasons For \nLender Check The following illustrates some of the r easons why a lender/other party would \nwant to check on a participant’s exclusion.  \n A lender hiring an underwriter for its  VA lending activities may want to \nverify that the underwriter is not an excluded party.  \n A lender making a loan to a veteran fo r new construction is told by another \nlender that the builder has had pr oblems with some of its HUD/FHA \ntransactions.  The lender may want to verify that the builder is not an \nexcluded party. \n A management broker establishing a pane l of contractors to do repairs to \nVA-owned properties must ensure th at none of the panel members are \nexcluded parties."
    },
    {
      "page": 6,
      "content": "Chapter 17:  VA Sanctions Against Program Participants VA Pamphlet 26-7, Revised  \n17-6   17.02  False Lender Certification \n \nLender \nCertification A lender must submit a signed certif ication with each loan submission \nindicating that in processing and und erwriting the loan, the lender has \ncomplied with  \n VA requirements \n regulations, and \n the law. \n \nThe specific language required in the certification is found in Step 7 of \n“Lender Procedures ” in Section 4.01. \n \nFalse Lender \nCertification Any lender who knowingly and willfully makes a false certification may be \nsubject to civil money penalties equal to the greater of  \n two times the amount of the Government’s loss on the loan involved, or \n another appropriate amount, not to exceed $10,000. \n \nIn addition to monetary penalties, VA  may impose other sanctions including, \nbut not limited to  \n debarment and suspension, and \n loss of automatic authority. \n \nLenders \nAssessed Monetary Penalty  Lenders assessed civil money penalties for a false certification do not appear \nin GSA’s  List of Parties Excluded From Federal Procurement and \nNonprocurement Programs .  Other program particip ants may still transact \nVA business with these lenders.  Exception :  Lenders may appear on the GS A list if another sanction is \nimposed against them in conjunction with  the civil money penalty.  In such \ncases, other program participants may be prohibited from transacting business \nwith them."
    },
    {
      "page": 7,
      "content": "VA Pamphlet 26-7, Revised  Chapter 17:  VA Sanctions Against Program Participants  \n  17-7  17.03  Withdrawal of Automatic Authority \n \nWithdrawal \nFor Proper \nCause VA can withdraw a lender’s automatic au thority for proper cause, after giving \nthe lender 30 days’ notice.   This applies to both  \n \n supervised, and \n nonsupervised lenders. \n \nSubmitting \nLoans for Prior \nApproval The lender may continue processing loans on a prior approval basis after \nautomatic authority has been withdrawn.  Note :  It is the lender’s res ponsibility to submit all loans for prior approval as \nlon\ng as automatic authorit y is withdrawn. \n \nVA Business \nWith Other \nParticipants Lenders with their automatic authority  withdrawn do not appear in GSA’s  \nList of Parties Excluded From Fe deral Procurement and Nonprocurement \nPrograms .  Other program participants ma y still transact VA business with \nthese lenders.  Exception :  Lenders may appear on the GS A list if another sanction is \nimposed against them.  In such cases , other program participants may be \nprohibited from transactin\ng business with them. \n \nWithdrawal for \nan Indefinite \nPeriod Withdrawal for an indefin ite period can be based on \n \n failure to continue mee ting basic qualifying criteria \n for supervised lenders this  includes loss of status as  an entity subject to \nexamination and supervision by a Fe deral or state regulatory agency \n for nonsupervised lenders this includ es no approved underwriter, failure \nto maintain $50,000 working capital, and/ or failure to file the required \nfinancial statements \n any of the causes for debarment set forth in 38 CFR 44.305 , or \n poor underwriting or consistently  careless processing during the \nprobationary period for newly-approv ed nonsupervised automatic lenders. \n \n[38 CFR 44.305 ] \n \nContinued on next page"
    },
    {
      "page": 8,
      "content": "Chapter 17:  VA Sanctions Against Program Participants VA Pamphlet 26-7, Revised  \n17-8   17.03  Withdrawal of Automatic Authority, Continued \n \nWithdrawal \nTime Periods Refer to the following table for info rmation on withdrawal time periods. \n \nWithdrawal \nPeriod:  60 Days A withdrawal period of 60 days can  be based on any of the following \nsituations:  \n Loan submissions show deficiencies in  credit underwriting after repeatedly \nbeing called to the lender's attention. \n Use of unstable sources of income  to qualify borrower or ignoring \nsignificant adverse credit items aff ecting applicant’s creditworthiness. \n Employment or deposit veri fications are hand-carri ed by applicants or \notherwise improperly permitted to pass through the hands of a third party. \n Loan submissions are consistently incomplete after repeatedly being called \nto the lender's attention \n There are continued instances of disregard of VA requirements after \nrepeatedly being called to the lender's attention. \n \nContinued on next page"
    },
    {
      "page": 9,
      "content": "VA Pamphlet 26-7, Revised  Chapter 17:  VA Sanctions Against Program Participants  \n  17-9  17.03  Withdrawal of Automatic Authority, Continued \n \nWithdrawal \nPeriod:  180 \nDays A withdrawal period of 180 days can be based on any of the following \nsituations:  \n Loans conflict with VA credit standard s and would not have been made by \na lender acting prudently. \n Failure to disclose to VA significant obligations or other information which \naffects the veteran’s ability to repa y the loan, and which results in undue \nrisk to the Government. \n Employment or deposit veri fications are handcarried  by the applicant or \notherwise mishandled, resulting in su bmission of significant misinformation \nto VA. \n Substantiated complaints are received that the lender misrepresented VA \nrequirements to veterans  to the detriment of their interests. \n \nExample  \nThe veteran was dissuaded from seeking a lower interest rate based on the \nlender's incorrect advice that su ch options were excluded by VA \nrequirements.  \n Closing documents show instances of improper charges to veteran after the \nimpropriety of such char ges are called to lender’s attention by VA, or the \nlender refuses to refund such ch arges after notification by VA. \n Deliberate delays in sc heduling loan closings. \n \nContinued on next page"
    },
    {
      "page": 10,
      "content": "Chapter 17:  VA Sanctions Against Program Participants VA Pamphlet 26-7, Revised  \n17-10   17.03  Withdrawal of Automatic Authority, Continued \n \nWithdrawal \nPeriod:  1-3 \nYears A withdrawal period of 1- 3 years can be based on any of the situations \ndescribed in the table below. \n \nSituation Example \nFailure to properly disburse loan s Loan disbursement checks are \nreturned due to insufficient funds. \nInvolvement by the lender in the improper use of a veteran's entitlement Knowingly permitting the veteran to \nviolate occupancy requirements, or lender involvement in the veteran’s sale of entitlement to a third part\ny. \n Lender makes the loan with the \nknowledge that the veteran is not purchasing the property to be his or her home.  Instead, the veteran intends to transfer title to a third party who assumes the loan shortly after closin\ng."
    },
    {
      "page": 11,
      "content": "VA Pamphlet 26-7, Revised  Chapter 17:  VA Sanctions Against Program Participants  \n  17-11  17.04  Withdrawal of LAPP Authority \n  \nLAPP is a \nPrivilege The authority to determine value under  LAPP is a privilege delegated to \nlenders at VA’s discretion.  Lenders ma intain this privilege by complying \nwith all applicable LAPP-related VA requirements.  \n  \nWithdrawal or \nAmendment for \nProper Cause VA can amend or withdraw the specia l privilege of LAPP authority from a \nlender for proper cause.  This applies to both supervised and nonsupervised \nlenders with automatic authorit y that have been granted LAPP authorit y. \n   \nWithdrawal \nTime Period LAPP authority can be withdrawn for a sp ecific or indefinite period of time. \n \nContinued on next page"
    },
    {
      "page": 12,
      "content": "Chapter 17:  VA Sanctions Against Program Participants VA Pamphlet 26-7, Revised  \n17-12   17.04  Withdrawal of LAPP Authority, Continued \n \nExamples of \nWithdrawal for \nProper Cause The following is a non-inclusive list of  examples of proper cause that can \nform a basis for withdrawal of LAPP authority.  Technical incompetence  \nConduct demonstrating insu fficient knowledge of i ndustry-accepted appraisal \nprinciples, techniques and practices and/ or the inability to adequately apply \nthem in reviewing appraisal reports and making value determinations for VA \npurposes.  Substantive or repetitive errors  \nA substantive error is one which significantly involves the value determination or c ondition of the property.  In the aggregate, nonsubstantive \nerrors which are frequently repeated may also indicate that LAPP case reviews are being performed in a careless or negligent manner.  \n \nDisregard for VA requirements  \nContinued disregard for the VA requirements and procedures outlined in VA regulations, guidelines, inst ructions or applicable la ws, after the problem has \nbeen brought to the le nder's attention. \n Failure to meet qualification requirements  \nThe lender or the lender’s staff apprai sal reviewer (SAR) no longer meets the \nbasic LAPP qualification requirements (see Chapter 15).  Civil judgments and convictions  \n \nContinued on next page"
    },
    {
      "page": 13,
      "content": "VA Pamphlet 26-7, Revised  Chapter 17:  VA Sanctions Against Program Participants  \n  17-13  17.04  Withdrawal of LAPP Authority, Continued \n \nNotice of \nSanction Generally, VA will provide written notice at least 30 days prior to imposition \nof the sanction to  \n the lender’s staff appr aisal reviewer (SAR) \n the lending officer responsible for the quality of the SAR’s work, and \n any other appropria te official(s). \n \nNote :  VA’s notice provides the basis fo r the sanction a nd information on \nhow to exercise appeal ri ghts. \n \nGovernment at \nImmediate Risk VA is not required to give 30 days’ noti ce if the Government’s interests are \nexposed to immediate risk from the le nder’s activities.  The withdrawal is \neffective immediatel y in such cases. \n \nDetermining \nReasonable \nValue and Issuing CRVs Once LAPP authority is withdrawn, VA must \n \n make all determinations of reas onable value for the lender, and \n issue the Certificates of  Reasonable Value (CRVs). \n \nNote :  For any withdrawal longer than 90 days, the lender must reapply to VA \nto participate in LAPP. \n \nImposition of \nProbationary \nPeriod As an alternative, VA may impose a probationary period for a specified \nperiod to further evaluate LAPP-related performance.  During that period, the \nVA office, at its discretion, may require  \n VA review of appraisal reports  and lender notices of value \n VA staff issuance of the lender’s VA value notices \n increased VA quality control review of the lender's LAPP cases, or \n other measures designed to m onitor and improve performance. \n \nContinued on next page"
    },
    {
      "page": 14,
      "content": "Chapter 17:  VA Sanctions Against Program Participants VA Pamphlet 26-7, Revised  \n17-14   17.04  Withdrawal of LAPP Authority, Continued \n \nOther \nSanctions Withdrawal or amendment of a lende r’s LAPP authority does not preclude \nVA from  \n also withdrawing automatic processing authority, or \n taking debarment or suspension actio n against the lender for the same \ncause. \n \nRelationship \nWith Other \nProgram Participants Lenders with their LAPP authority w ithdrawn do not appear in GSA’s List of \nParties Excluded From Federal Procurement and Nonprocurement \nPrograms.  Other program participants may still tr ansact VA business with these lenders. \n Exception :  Lenders may appear on the GS A list if another sanction is \nimposed against them.  In such cases , other program participants may be \nprohibited from transactin\ng business with them. \n \nResponsbilities \nof Lender As long as LAPP authority is withdraw n, it is the lender’s responsibility to \nensure that VA, and not the lender  \n makes all determinations of  reasonable value, and \n issues CRVs on its loans."
    },
    {
      "page": 15,
      "content": "VA Pamphlet 26-7, Revised  Chapter 17:  VA Sanctions Against Program Participants  \n  17-15  17.05  Debarment and Suspension \n \nDebarment Debarment is a sanction that in most cases excludes the program participant \nfrom any participation in the nonproc urement programs of any Federal \nagency, including VA’s loan guaranty program.  Note :  Occasionally debarment is used to exclude the participant from only \ncertain t\nypes of transactions. \n \nDebarment \nTime Period Debarment is effective for a period a ppropriate to the seriousness of the \ncause.  Often a period of 3 years is deemed appropriate. \n \nSuspension Suspension has the same impact as deba rment, but is imposed on a temporary \nbasis, pending the outcome of  \n investigative \n legal, or \n debarment proceedings. \n \nNote :  Suspension can be followed by debarment if the results of the \nproceedin gs warrant. \n \nSuspension \nTime Period Suspension generally does not exceed  18 months.  It is imposed for a \ntemporary period pending  \n investigative \n legal, or \n debarment proceedings. \n \nNote :  An additional period of debarment may follow. \n \nContinued on next page"
    },
    {
      "page": 16,
      "content": "Chapter 17:  VA Sanctions Against Program Participants VA Pamphlet 26-7, Revised  \n17-16   17.05  Debarment and Suspension, Continued \n \nGeographic \nScope of \nExclusion The debarred or suspended participant is excluded from targeted activities in \nall locations. \n \nDebarred Loan \nGuaranty Participants All loan guaranty program participants debarred  by VA are listed in GSA’s \nList of Parties Excluded From Federal Nonprocurement Programs .  Most of \nthese debarments are Government-wide.  The GSA list contains government-wid e debarments of parties who cannot  \nparticipate in the nonprocurement pro\ngrams of an y Federal a gency.   \n \nParticipant is \nan Entity Any program participant (ind ividual or entity) and/or affiliate can be debarred \nor suspended.  If the participant is an  entity, the sanction can be imposed \nagainst the   \n entire organization \n a certain part of the organization, or \n only certain individuals. \n \nVA Regulations VA can impose debarments or suspensi ons based on any of a multitude of \ncauses outlined in VA regulations  \n 38 CFR 44.305 , and \n 38 CFR.44.405 . \n[38 CFR 44.305 ] \n[38 CFR 44.405 ] \n \nContinued on next page"
    },
    {
      "page": 17,
      "content": "VA Pamphlet 26-7, Revised  Chapter 17:  VA Sanctions Against Program Participants  \n  17-17  17.05  Debarment and Suspension, Continued \n \nCauses for \nDebarment or \nSuspension The regulations authorize VA to debar or  suspend participants for “Any other \ncause of so serious or compelling a nature that it affects the present \nresponsibility of a person.”  These ca uses include, but are not limited to \n \n conviction of, or civil judgment for, fraud, embezzl ement, theft, forgery, \nfalsification or dest ruction of records, commission of an offense evidencing \nserious lack of integrity \n violation of the terms of a public agreement or trans action so serious as to \naffect the integrity of an agency program \n knowingly doing business with a deba rred, suspended, ineligible, or \nvoluntarily excluded person, or \n failure to pay debts owed to the Federal Government. \n \n[38 CFR 44.305 ] \n[38 CFR 44.405 ]"
    },
    {
      "page": 18,
      "content": "Chapter 17:  VA Sanctions Against Program Participants VA Pamphlet 26-7, Revised  \n17-18   17.06  Limited Denial of Participation (LDP) \n \nIntroduction A Limited Denial of Participation (LDP) \n \n is a sanction imposed by a local VA o ffice limiting a progr am participant’s \nactivities within that local VA office’s jurisdiction \n can either exclude the program participant from  participation in any VA \nloan guaranty activities in the geographi c area or just certain types of loan \nguaranty activities in the geographic area, and \n can be the sole sanction against a par ticipant, or a means to immediately \nend unacceptable conduct while more se vere sanctions are considered. \n \nNote:   An LDP may prohibit the particip ant from performing VA appraisals, \nbut not from actin g as a mana gement broker or in another role. \n \nParticipant is \nan Entity If the participant is an entity, th e sanction can be imposed against \n \n the entire organization \n a certain part of the organization, or \n only certain individuals. \n \nLDP \nExceptions An LDP can be imposed against any program participan t (individual or \nentity) and/or affiliate except  \n lenders \n employees of lenders, and \n manufactured home manufacturers. \n \nContinued on next page"
    },
    {
      "page": 19,
      "content": "VA Pamphlet 26-7, Revised  Chapter 17:  VA Sanctions Against Program Participants  \n  17-19  17.06  Limited Denial of  Participation (LDP), Continued \n \nCauses for LDP VA can impose LDPs based on any of a multitude of causes outlined in VA \nregulations 38 CFR 44.705 .  These causes include, but are not limited to \n \n irregularities in a participant’s or contractor’s performance in the VA loan \nguaranty program \n failure to satisfy contractual obligatio ns or to proceed in accordance with \ncontract specifications \n construction deficiencies deemed  by VA to be the participant’s \nresponsibility, and \n failure to proceed in accordance with VA requirements or to comply with \nVA regulations. \n[38 CFR 44.705 ] \n \nLDP as \nReciprocal \nAction A local VA office may also impose an LD P as a reciprocal action because an \nLDP or other sanction was im posed upon the participant by \n \n another VA office, or \n an office of another Federal agency, such as HUD or USDA. \n \nA VA office may also notify local offices of another Federal agency that the \nLDP action has been taken. \n \nJurisdiction \nRestrictions The participant is excluded from targeted activities only  within the \njurisdiction of the VA office imposin g the sanction.  If other VA offices \nimpose a reciprocal LDP, the ex clusion applies within their jurisdictions also. \n \nContinued on next page"
    },
    {
      "page": 20,
      "content": "Chapter 17:  VA Sanctions Against Program Participants VA Pamphlet 26-7, Revised  \n17-20   17.06  Limited Denial of  Participation (LDP), Continued \n \nAppeal Rights No additional appeal rights are provided to the participant for reciprocal \nLDPs.  The participant is provided app eal rights with the original LDP only, \nand ma y choose to exercise them at that time. \n \nLDP Time \nPeriod LDPs can be imposed for a sp ecified period up to 12 months. \n \nBuilders With \nUnresolved Deficiencies In the case of builders  with unresolved construction deficiencies, the LDP \nmay be for  \n an indefinite period pend ing correction of the cons truction deficiencies, or \n a specified period up to 12 months. \n \nObtaining LDP \nParty \nInformation LDP parties are not listed in GSA’s List of Parties Excluded From Federal \nProcurement and Nonprocurement Programs .  Therefore, information must \nbe obtained from the local VA office."
    },
    {
      "page": 21,
      "content": "VA Pamphlet 26-7, Revised  Chapter 17:  VA Sanctions Against Program Participants  \n  17-21  17.07  Unfair Contract Provis ions or Marketing Practices \n \nIntroduction VA may impose sanctions, such as de barment, suspension, or LDP against \nparticipants who use contracts of sa le, or methods or practices in the \nmarketing of properties, which are unfair  or prejudicial to veteran-purchasers. \nUnethical practices based upon experien ce and standards generally observed \nby reputable homebuilders and other reputable progr am participants are \n \n barred by VA, and \n grounds for sanctions. \n \nNote :  Chapter 9 provides examples of unfair contractual provisions or \nfeatures. \n  \nContinued on next page"
    },
    {
      "page": 22,
      "content": "Chapter 17:  VA Sanctions Against Program Participants VA Pamphlet 26-7, Revised  \n17-22   17.07  Unfair Contract Provis ions or Marketing Practices, \nContinued \n \nUnfair \nMarketing \nPractices Unfair marketing practices include, but are not limited to \n \n enforcement of unfair co ntractual provisions \n requiring purchasers to execute so-ca lled “contracts” which legally bind the \npurchasers but do not bind the seller to deliver the property when completed to the purchasers \n \nExample :  limiting a seller’s liability to the refund of the earnest money \ndeposit \n \n advertising that a property or projec t is “VA guaranteed” or “VA approved” \nor “VA inspected” in such a way as to  lead veterans to believe that VA \nguarantees the construction and workmanship Note :  “VA financing available,” “Eligi ble for VA financing,” or similar \nadvertising is acceptable. \n \n delaying tactics on the part of the bu ilder to postpone completion of the \nproperty or the closing of the sale after completion in an effort to induce the \nveteran to agree to a modificati on of a firm contract such as \n the substitution of inferior materials \n the omission of appliances, or \n an increase in price. \n \n failure of the seller or agent of the seller of proposed or newly constructed \nproperty to place deposits or downp ayments received from veteran-\npurchasers in a special trust account , as required by 38 U.S.C. 3706 \n failure to place downpayments or ea rnest money deposits in a trust fund \nor in escrow when required by law or by local practice on existing properties, or \n failure or inability of the seller to re turn the deposit when and if required \nunder the contract when it is not re quired or not customary for these \ndeposits to be “isolated,” and \n[38 U.S.C. 3706 ] \n \n failure of the seller of proposed or newl y constructed property to state in the \nsales agreement, when applicable, that the property was or will be \nconstructed under FHA compliance insp ection procedures pursuant to \nsection 203(i) or 221(d)(2) of the National Housing Act."
    },
    {
      "page": 23,
      "content": "VA Pamphlet 26-7, Revised  Chapter 17:  VA Sanctions Against Program Participants  \n  17-23  17.08  Violations of Equal Housing Opportunity Laws \n \nIntroduction VA may impose sanctions, such as de barment, suspension, or LDP against \nparticipants who violate st atutory provisions and re gulations governing equal \nopportunity in housing.  These la ws and regulations include \n \n Equal Credit Opportunity Act (ECOA) \n The Fair Housing Act \n Section 527 of the Nation al Housing Act, and \n VA Regulations at 38 CFR 36.4363  \n[38 CFR 36.4363 ] \n \nBased on these provisions and VA’s polic y on unfair market ing practices, VA \nmay impose sanctions if a ny party involved or financ ially interested in the \nconstruction or sale of property has dec lined to sell property to an eligible \nveteran because of \n \n race \n color \n sex \n handicap \n familial status \n religion, or \n national origin. \n \nContinued on next page"
    },
    {
      "page": 24,
      "content": "Chapter 17:  VA Sanctions Against Program Participants VA Pamphlet 26-7, Revised  \n17-24   17.08  Violations of Equa l Housing Opportunity Laws, Continued \n \nEqual Housing \nCertification  This regulation requires a certification by builders or other parties requesting \nthe following types of VA appraisals  \n a Master Certificate of Reasonable Va lue on proposed or existing housing, \nor \n an individual appraisal of existing housing that was not previously \noccupied. \n \nThe certification provides that the build er or other party will not decline to \nsell the appraised property to a prosp ective purchaser because of his or her \n \n race \n color \n religion \n sex, or \n national origin. \n \nNote :  This requirement is satisfie d by completion of VA Form 26-8791, VA \nAffirmative Marketin g Certi fication.  \n \nVeteran Equal \nHousing Certification Any veteran obtaining a VA-guara nteed loan is also requir ed to certify that he \nor she will not decline to sell the home in the future based on these discriminatory factors.  The certification is found in the Veteran’s \nCertifications on VA Form 26-1820 , Report and Certification of Loan \nDisbursement ."
    },
    {
      "page": 25,
      "content": "VA Pamphlet 26-7, Revised  Chapter 17:  VA Sanctions Against Program Participants  \n  17-25   \nAmend or Withdraw the Special Privilege of \nLAPP Authority, 17-11 \nAppeal Rights to all Program Participants, \n17-1 \nCause and Treatment Codes, 17-4 Causes for LDP, 17-19 Debarment, 17-15 Debarment or Suspension Causes, 17-17 Debarred Loan Guaranty Participants, 17-16 Determining Reasonable Value and Issuing \nCRVs, 17-13 \nDisregard for VA Requirements - Example, \n17-12 \nEqual Housing Certification, 17-24 Excluded Party, 17-4 Failure to Meet Qualification  Requirements \n- Example, 17-12 \nFalse Lender Certification, 17-6 Full Exclusion, 17-3 Government at Risk, 17-13 GSA List, 17-4 Identifying Excluded Parties Internet \nAddress, 17-3 \nJurisdiction Restrictions, 17-19 \nLAPP Privilege, 17-11 LDP as Reciprocal Action, 17-19 LDP Exceptions, 17-18 LDP Party Information, 17-20 LDP Time Period, 17-20 Limited Denial of Participation (LDP), 17-\n18 \nMonetary Penalty, 17-6 Nature of Exclusion, 17-4 Non Procurement List, 17-4 Notice of Sanction, 17-13 Other Program Participants, 17-14 Partial Exclusion, 17-3 Participant Also A Veteran, 17-2 Participant is an Entity, 17-16, 17-18 \nParticipants who Violate Statutory \nProvisions and Regulations, 17-23 \nProbationary Period, 17-13 Program Participants, 17-2 Reasons For Lender Check, 17-5 Responsbilities of Lender, 17-14 Sanctions, 17-1 Scope of Exclusion, 17-16 Submitting Loans, 17-7 Substantive or Repetitive Errors - Example, \n17-12 \nSuspension, 17-15 Technical Incompet ence - Withdrawal \nExample, 17-12 \nType of Participant, 17-1 Unfair Contract Prov isions or Marketing \nPractices, 17-21 \nUnfair Marketing Practices, 17-22 \nUnresolved Deficiencies, 17-20 VA Business With Other Participants, 17-7 VA Loan Guaranty Program, 17-1 VA May Impose Sanctions, 17-21 \nVA Regulations on Debarments or \nSuspensions, 17-16 \nVA’s Policy on Unfair Marketing Practices, \n17-23 \nVerifying Excluded Parties, 17-5 Veteran Equal Housing Certification, 17-24 Violations of Equal Housing Opportunity \nLaws, 17-23 \nWithdrawal for an Indefinite Period, 17-7 Withdrawal For Proper Cause, 17-7 Withdrawal Period:  1-3 Years, 17-10 \nWithdrawal Period:  180 Days, 17-9 Withdrawal Period:  60 Days, 17-8 Withdrawal Time Periods, 17-8"
    }
  ],
  "id": "9e8862bb-8f40-41d2-9fdb-9e85d2031760"
}